jaxmix/__init__.py
jaxmix/distributions.py
jaxmix/generative.py
jaxmix/io.py
jaxmix/jax_distributions.py
jaxmix/smc.py
jaxmix-0.1.0.dist-info/licenses/LICENSE
jaxmix-0.1.0.dist-info/METADATA
jaxmix-0.1.0.dist-info/WHEEL
jaxmix-0.1.0.dist-info/top_level.txt
jaxmix-0.1.0.dist-info/RECORD
